CITATION
LICENSE
MANIFEST.in
README
setup.py
dlmontepython/__init__.py
dlmontepython/dlm_wham.py
dlmontepython.egg-info/PKG-INFO
dlmontepython.egg-info/SOURCES.txt
dlmontepython.egg-info/dependency_links.txt
dlmontepython.egg-info/requires.txt
dlmontepython.egg-info/top_level.txt
dlmontepython/fep/__init__.py
dlmontepython/fep/fep.py
dlmontepython/htk/__init__.py
dlmontepython/htk/ensemble.py
dlmontepython/htk/histogram.py
dlmontepython/htk/multihistogram.py
dlmontepython/htk/obs.py
dlmontepython/htk/parameter.py
dlmontepython/htk/util.py
dlmontepython/htk/sources/__init__.py
dlmontepython/htk/sources/dlcell.py
dlmontepython/htk/sources/dlconfig.py
dlmontepython/htk/sources/dlcontrol.py
dlmontepython/htk/sources/dlfeddat.py
dlmontepython/htk/sources/dlfedflavour.py
dlmontepython/htk/sources/dlfedmethod.py
dlmontepython/htk/sources/dlfedorder.py
dlmontepython/htk/sources/dlfield.py
dlmontepython/htk/sources/dlfieldspecies.py
dlmontepython/htk/sources/dlgen_config.py
dlmontepython/htk/sources/dlinteraction.py
dlmontepython/htk/sources/dlmonte.py
dlmontepython/htk/sources/dlmonte_filter.py
dlmontepython/htk/sources/dlmove.py
dlmontepython/htk/sources/dlptfile.py
dlmontepython/htk/sources/dlspcgroup.py
dlmontepython/htk/sources/dlsymmetryoperation.py
dlmontepython/htk/sources/dlthreebody.py
dlmontepython/htk/sources/dlunits.py
dlmontepython/htk/sources/dlutil.py
dlmontepython/htk/sources/ising.py
dlmontepython/htk/sources/isingdata.py
dlmontepython/htk/tests/__init__.py
dlmontepython/htk/tests/test_dlconfig.py
dlmontepython/htk/tests/test_dlcontrol.py
dlmontepython/htk/tests/test_dlfedflavour.py
dlmontepython/htk/tests/test_dlfedmethod.py
dlmontepython/htk/tests/test_dlfedorder.py
dlmontepython/htk/tests/test_dlfield.py
dlmontepython/htk/tests/test_dlinteraction.py
dlmontepython/htk/tests/test_dlmonte.py
dlmontepython/htk/tests/test_dlmove.py
dlmontepython/htk/tests/test_dlptfile.py
dlmontepython/htk/tests/test_dlunits.py
dlmontepython/htk/tests/test_dlutil.py
dlmontepython/htk/tests/test_ensemble.py
dlmontepython/htk/tests/test_histogram.py
dlmontepython/htk/tests/test_ising.py
dlmontepython/htk/tests/test_multihistogram.py
