Metadata-Version: 2.1
Name: dlmontepython
Version: 0.1.dev15
Summary: Tools associated with the Monte Carlo simulation program DL_MONTE
Home-page: https://gitlab.com/dl_monte/dlmontepython
License: BSD License (BSD-3-Clause)
Platform: UNKNOWN
Classifier: Development Status :: 3 - Alpha
Classifier: Intended Audience :: Science/Research
Classifier: License :: OSI Approved :: BSD License
Classifier: Programming Language :: Python :: 3.8
Classifier: Topic :: Scientific/Engineering
